setup.py
redis_simple_queue/__init__.py
redis_simple_queue.egg-info/PKG-INFO
redis_simple_queue.egg-info/SOURCES.txt
redis_simple_queue.egg-info/dependency_links.txt
redis_simple_queue.egg-info/top_level.txt
test/__init__.py
test/test_redis_queue.py